audio_recaptchav2_solver/__init__.py
audio_recaptchav2_solver/solver.py
audio_recaptchav2_solver/transcriber.py
audio_recaptchav2_solver/web_utils.py
audio_recaptchav2_solver-0.1.0.dist-info/METADATA
audio_recaptchav2_solver-0.1.0.dist-info/WHEEL
audio_recaptchav2_solver-0.1.0.dist-info/RECORD
