Metadata-Version: 2.1
Name: audio-recaptchav2-solver
Version: 0.1.0
Summary: 
Author: Hirthick Raj
Author-email: hirthickraj@jmangroup.com
Requires-Python: >=3.11,<4.0
Classifier: Programming Language :: Python :: 3
Classifier: Programming Language :: Python :: 3.11
Classifier: Programming Language :: Python :: 3.12
Requires-Dist: requests (>=2.31.0,<3.0.0)
Requires-Dist: selenium (>=4.20.0,<5.0.0)
Requires-Dist: whisper (>=1.1.10,<2.0.0)
